<?xml version="1.0" encoding="UTF-8"?>
<metadata xml:lang="en"><Esri><CreaDate>20220222</CreaDate><CreaTime>17083100</CreaTime><ArcGISFormat>1.0</ArcGISFormat><SyncOnce>TRUE</SyncOnce><DataProperties><itemProps><itemLocation><linkage Sync="TRUE">file://\\fses52-003\mulligans\MULLIGANS-GOOROOYARROO\DATA\GIS\MFGO\Goorooyarroo\GNR</linkage><protocol Sync="TRUE">Local Area Network</protocol></itemLocation></itemProps><copyHistory><copy source="Z:\MULLIGANS-GOOROOYARROO\DATA\GIS\MFGO\GNR" dest="\\fses52-003\mulligans\MULLIGANS-GOOROOYARROO\DATA\GIS\MFGO\Goorooyarroo\GNR" date="20220222" time="17083100"></copy></copyHistory></DataProperties></Esri></metadata>
